frontend_editables/__init__.py
frontend_editables/_core.py
frontend_editables/_redirector.py
frontend_editables/_utils.py
frontend_editables/transitional_cli.py
frontend_editables-0.2.0.dist-info/COPYING
frontend_editables-0.2.0.dist-info/WHEEL
frontend_editables-0.2.0.dist-info/METADATA
frontend_editables-0.2.0.dist-info/RECORD
