Metadata-Version: 2.1
Name: frontend-editables
Version: 0.2.0
Summary: A library for installing distributions in editable mode.
Author-email: layday <layday@protonmail.com>
Requires-Python: >=3.6
Requires-Dist: typing-extensions >=3.10.0.0
Requires-Dist: coverage[toml] ; extra == "test"
Requires-Dist: pytest ; extra == "test"
Project-URL: changelog, https://github.com/layday/frontend-editables/blob/main/CHANGELOG.rst
Project-URL: homepage, https://github.com/layday/frontend-editables
Project-URL: repository, https://github.com/layday/frontend-editables
Provides-Extra: test
